{"language":"en-US","region":"US","quoteType":"EQUITY","quoteSourceName":"Delayed Quote","triggerable":false,"currency":"EUR","firstTradeDateMilliseconds":898671600000,"priceHint":2,"marketState":"REGULAR","exchange":"GER","shortName":"Adidas AG","exchangeTimezoneName":"Europe\/Berlin","exchangeTimezoneShortName":"CEST","gmtOffSetMilliseconds":7200000,"market":"de_market","esgPopulated":false,"trailingPE":98.60314,"pegRatio":1.23,"epsTrailingTwelveMonths":2.792,"sharesOutstanding":195032992,"bookValue":31.943,"fiftyDayAverage":268.6706,"fiftyDayAverageChange":6.6293945,"fiftyDayAverageChangePercent":0.024674805,"twoHundredDayAverage":237.4003,"twoHundredDayAverageChange":37.89969,"twoHundredDayAverageChangePercent":0.15964465,"marketCap":53692579840,"priceToBook":8.618476,"sourceInterval":15,"exchangeDataDelayedBy":0,"tradeable":false,"totalCash":2382000130,"ebitda":2318000128,"regularMarketChange":1.7999878,"regularMarketChangePercent":0.6581308,"regularMarketTime":1601984910,"regularMarketPrice":275.3,"regularMarketDayHigh":275.3,"regularMarketDayRange":"272.0 - 275.3","regularMarketDayLow":272,"regularMarketVolume":88780,"regularMarketPreviousClose":273.5,"bid":275.3,"ask":275.4,"fullExchangeName":"XETRA","regularMarketOpen":273,"averageDailyVolume3Month":537075,"beta":0.836206,"fiftyTwoWeekLowChange":113.09999,"fiftyTwoWeekLowChangePercent":0.69728726,"fiftyTwoWeekRange":"162.2 - 317.45","fiftyTwoWeekHighChange":-42.150024,"fiftyTwoWeekHighChangePercent":-0.13277689,"fiftyTwoWeekLow":162.2,"fiftyTwoWeekHigh":317.45,"exDividendDate":1589500800,"symbol":"ADS.DE"}